gruv_socks/__init__.py
gruv_socks/gruv_socks.py
gruv_socks-0.9.8.dist-info/LICENSE
gruv_socks-0.9.8.dist-info/METADATA
gruv_socks-0.9.8.dist-info/WHEEL
gruv_socks-0.9.8.dist-info/top_level.txt
gruv_socks-0.9.8.dist-info/RECORD
