Metadata-Version: 2.1
Name: gruv-socks
Version: 0.9.8
Summary: Easy to use standard for abstracting the work needed to transport and reconstruct messages over TCP.
Home-page: https://github.com/ForestJ2/gruv_socks
Author: Forest Jacobsen
License: UNKNOWN
Platform: UNKNOWN
Classifier: Programming Language :: Python :: 3.9
Classifier: License :: OSI Approved :: MIT License
Classifier: Operating System :: OS Independent
